sax/__init__.py
sax/circuits.py
sax/constants.py
sax/fit.py
sax/interpolation.py
sax/loss.py
sax/multimode.py
sax/netlists.py
sax/ports.py
sax/s.py
sax/utils.py
sax/backends/__init__.py
sax/backends/additive.py
sax/backends/filipsson_gunnar.py
sax/backends/forward_only.py
sax/backends/klu.py
sax/models/__init__.py
sax/models/bends.py
sax/models/couplers.py
sax/models/crossings.py
sax/models/factories.py
sax/models/mmis.py
sax/models/probes.py
sax/models/rf.py
sax/models/splitters.py
sax/models/straight.py
sax/parsers/__init__.py
sax/parsers/lumerical.py
sax/parsers/touchstone.py
sax/saxtypes/__init__.py
sax/saxtypes/anymode.py
sax/saxtypes/core.py
sax/saxtypes/custom_warnings.py
sax/saxtypes/into.py
sax/saxtypes/multimode.py
sax/saxtypes/netlist.py
sax/saxtypes/settings.py
sax/saxtypes/singlemode.py
sax-0.16.3.dist-info/licenses/LICENSE
tests/__init__.py
tests/test_circuit.py
tests/test_nbs.py
tests/test_netlist.py
tests/test_probes.py
tests/test_rf_models.py
sax-0.16.3.dist-info/METADATA
sax-0.16.3.dist-info/WHEEL
sax-0.16.3.dist-info/top_level.txt
sax-0.16.3.dist-info/RECORD
