Metadata-Version: 2.4
Name: sax
Version: 0.16.3
Summary: Autograd and XLA for S-parameters
Author-email: Floris Laporte <floris.laporte@gmail.com>
License: Apache Software License
Keywords: simulation,optimization,autograd,simulation-framework,circuit,physics-simulation,photonics,s-parameters,jax,xla,photonic-circuit,photonic-optimization
Classifier: Development Status :: 3 - Alpha
Classifier: Intended Audience :: Science/Research
Classifier: License :: OSI Approved :: Apache Software License
Classifier: Operating System :: OS Independent
Classifier: Programming Language :: Python :: 3.11
Classifier: Programming Language :: Python :: 3.12
Classifier: Programming Language :: Python :: 3.13
Classifier: Programming Language :: Python :: 3.14
Classifier: Topic :: Scientific/Engineering
Classifier: Topic :: Scientific/Engineering :: Physics
Requires-Python: >=3.11.0
License-File: LICENSE
Requires-Dist: flax>=0.10.0
Requires-Dist: jax
Requires-Dist: jaxtyping>=0.2.38
Requires-Dist: klujax>=0.4.1
Requires-Dist: lark>=1.2.2
Requires-Dist: matplotlib>=3.0.0
Requires-Dist: natsort>=8.0.0
Requires-Dist: networkx>=3.0.0
Requires-Dist: numpy>=2.2.0
Requires-Dist: orjson>=3.0.0
Requires-Dist: pydantic>=2.10.0
Requires-Dist: pyyaml>=6.0.0
Requires-Dist: scikit-rf>=1.8.0
Requires-Dist: sympy>=1.14.0
Requires-Dist: typing-extensions>=4.13.2
Requires-Dist: xarray>=2025.1.2
Provides-Extra: dev
Requires-Dist: altair>=5.5.0; extra == "dev"
Requires-Dist: optax>=0.2.0; extra == "dev"
Requires-Dist: build>=1.2.0; extra == "dev"
Requires-Dist: gdsfactory>=9.32.0; extra == "dev"
Requires-Dist: griffe>=1.5.6; extra == "dev"
Requires-Dist: ipykernel>=6.29.5; extra == "dev"
Requires-Dist: matplotlib>=3.10.0; extra == "dev"
Requires-Dist: meow-sim>=0.14.0; extra == "dev"
Requires-Dist: mkautodoc>=0.2.0; extra == "dev"
Requires-Dist: mkdocs-autorefs>=1.3.0; extra == "dev"
Requires-Dist: mkdocs-bibtex>=4.4.0; extra == "dev"
Requires-Dist: mkdocs-material>=9.6.0; extra == "dev"
Requires-Dist: mkdocs>=1.6.1; extra == "dev"
Requires-Dist: mkdocstrings[python]>=0.27.0; extra == "dev"
Requires-Dist: mkinit>=1.1.0; extra == "dev"
Requires-Dist: nbconvert>=7.16.6; extra == "dev"
Requires-Dist: papermill>=2.6.0; extra == "dev"
Requires-Dist: plotly>=6.0.0; extra == "dev"
Requires-Dist: pre-commit>=4.1.0; extra == "dev"
Requires-Dist: pyright>=1.1.0; extra == "dev"
Requires-Dist: pytest-cov>=6.0.0; extra == "dev"
Requires-Dist: pytest-randomly>=3.16.0; extra == "dev"
Requires-Dist: pytest-xdist>=3.6.0; extra == "dev"
Requires-Dist: pytest>=8.3.0; extra == "dev"
Requires-Dist: ruff>=0.9.0; extra == "dev"
Requires-Dist: scikit-learn>=1.6.1; extra == "dev"
Requires-Dist: bver; extra == "dev"
Requires-Dist: tmm>=0.2.0; extra == "dev"
Requires-Dist: towncrier>=24.0.0; extra == "dev"
Requires-Dist: vega-datasets>=0.9.0; extra == "dev"
Requires-Dist: nb-clean>=4.0.1; extra == "dev"
Requires-Dist: ty>=0.0.1a11; extra == "dev"
Requires-Dist: nbstripout>=0.8.1; extra == "dev"
Requires-Dist: mkdocs-matplotlib; extra == "dev"
Requires-Dist: scikit-rf>=1.8.0; extra == "dev"
Requires-Dist: pydot>=4.0.1; extra == "dev"
Dynamic: license-file
